code/__init__.py
code/hft_struct/Reader.py
code/hft_struct/__init__.py
code/hft_struct/book_ticker.py
code/hft_struct/exchange_info.py
code/hft_struct/market_snapshot.py
code/hft_struct/order.py
code/hft_struct/struct_util.py
code/util/__init__.py
code/util/factor.py
code/util/mploter.py
code/util/util.py
py_hft/__init__.py
py_hft/hft_struct/Reader.py
py_hft/hft_struct/__init__.py
py_hft/hft_struct/book_ticker.py
py_hft/hft_struct/exchange_info.py
py_hft/hft_struct/market_snapshot.py
py_hft/hft_struct/order.py
py_hft/hft_struct/struct_util.py
py_hft/util/__init__.py
py_hft/util/factor.py
py_hft/util/libconfig_check.py
py_hft/util/mploter.py
py_hft/util/util.py
py_hft-0.1.19.dist-info/METADATA
py_hft-0.1.19.dist-info/WHEEL
py_hft-0.1.19.dist-info/top_level.txt
py_hft-0.1.19.dist-info/RECORD
