Metadata-Version: 2.1
Name: py_hft
Version: 0.1.19
Summary: util for hft
Home-page: https://zhuanlan.zhihu.com/p/26
Author: arockie
Author-email: arockie123@gmail.com
License: MIT
Requires-Python: >=3.6.0
Requires-Dist: matplotlib
Requires-Dist: tqdm
Requires-Dist: psutil
Requires-Dist: pandas
Requires-Dist: tabulate
Requires-Dist: ipython
Requires-Dist: statsmodels
Requires-Dist: scipy
Requires-Dist: termcolor
Requires-Dist: jupyter
